yt_napari/__init__.py
yt_napari/_data_model.py
yt_napari/_ds_cache.py
yt_napari/_gui_utilities.py
yt_napari/_model_ingestor.py
yt_napari/_reader.py
yt_napari/_schema_version.py
yt_napari/_special_loaders.py
yt_napari/_version.py
yt_napari/_widget_matadata.py
yt_napari/_widget_reader.py
yt_napari/config.py
yt_napari/logging.py
yt_napari/napari.yaml
yt_napari/timeseries.py
yt_napari/viewer.py
yt_napari/_tests/__init__.py
yt_napari/_tests/conftest.py
yt_napari/_tests/test_config.py
yt_napari/_tests/test_covering_grid_json.py
yt_napari/_tests/test_ds_cache.py
yt_napari/_tests/test_gui_utilities.py
yt_napari/_tests/test_metadata_widget.py
yt_napari/_tests/test_model_ingestor.py
yt_napari/_tests/test_reader.py
yt_napari/_tests/test_regions_json.py
yt_napari/_tests/test_schema_manager.py
yt_napari/_tests/test_schema_version_comparisons.py
yt_napari/_tests/test_slices_json.py
yt_napari/_tests/test_timeseries.py
yt_napari/_tests/test_timeseries_json.py
yt_napari/_tests/test_viewer.py
yt_napari/_tests/test_widget_reader.py
yt_napari/schemas/__init__.py
yt_napari/schemas/_manager.py
yt_napari/schemas/_version_comparison.py
yt_napari-0.5.0.dist-info/LICENSE
yt_napari-0.5.0.dist-info/METADATA
yt_napari-0.5.0.dist-info/WHEEL
yt_napari-0.5.0.dist-info/entry_points.txt
yt_napari-0.5.0.dist-info/top_level.txt
yt_napari-0.5.0.dist-info/RECORD
