Metadata-Version: 2.1
Name: yt-napari
Version: 0.5.0
Summary: A napari plugin for loading data from yt
Home-page: https://github.com/data-exp-lab/yt-napari
Author: Chris Havlin
Author-email: chris.havlin@gmail.com
License: BSD-3-Clause
Project-URL: Bug Tracker, https://github.com/data-exp-lab/yt-napari/issues
Project-URL: Documentation, https://github.com/data-exp-lab/yt-napari#README.md
Project-URL: Source Code, https://github.com/data-exp-lab/yt-napari
Project-URL: User Support, https://github.com/data-exp-lab/yt-napari/issues
Classifier: Development Status :: 2 - Pre-Alpha
Classifier: Framework :: napari
Classifier: Intended Audience :: Developers
Classifier: License :: OSI Approved :: BSD License
Classifier: Operating System :: OS Independent
Classifier: Programming Language :: Python
Classifier: Programming Language :: Python :: 3
Classifier: Programming Language :: Python :: 3 :: Only
Classifier: Topic :: Software Development :: Testing
Requires-Python: >=3.8
License-File: LICENSE
Requires-Dist: magicgui >=0.6.1
Requires-Dist: napari >=0.4.19
Requires-Dist: numpy
Requires-Dist: packaging
Requires-Dist: pydantic >2.0
Requires-Dist: qtpy
Requires-Dist: unyt
Requires-Dist: yt >=4.0.1
Provides-Extra: dev
Requires-Dist: pytest ; extra == 'dev'
Requires-Dist: pytest-qt ; extra == 'dev'
Requires-Dist: taskipy ; extra == 'dev'
Provides-Extra: docs
Requires-Dist: sphinx ; extra == 'docs'
Requires-Dist: nbsphinx <0.8.8 ; extra == 'docs'
Requires-Dist: sphinx-jsonschema <1.19.0 ; extra == 'docs'
Requires-Dist: Jinja2 <3.1.0 ; extra == 'docs'
Provides-Extra: full
Requires-Dist: dask[array,distributed] ; extra == 'full'
